persistentMemory/PersistentMemory.py
persistentMemory/__init__.py
tests/__init__.py
tests/test_PersistentMemory.py
PersistentMemory-0.1.4.dist-info/LICENSE
PersistentMemory-0.1.4.dist-info/METADATA
PersistentMemory-0.1.4.dist-info/WHEEL
PersistentMemory-0.1.4.dist-info/top_level.txt
PersistentMemory-0.1.4.dist-info/RECORD
