Metadata-Version: 2.1
Name: PersistentMemory
Version: 0.1.4
Summary: Package for persistent memory
Author-email: ufukilke <ufukilkeavci@gmail.com>
Project-URL: Homepage, https://github.com/ufukilkeavci/persistentMemory
Project-URL: Issues, https://github.com/ufukilkeavci/persistentMemory/issues
Classifier: Programming Language :: Python :: 3
Classifier: License :: OSI Approved :: MIT License
Classifier: Operating System :: OS Independent
Requires-Python: >=3.8
License-File: LICENSE
